fooster_web-0.4.0rc1-py3.9-nspkg.pth
fooster/web/__init__.py
fooster/web/auth.py
fooster/web/fancyindex.py
fooster/web/file.py
fooster/web/form.py
fooster/web/json.py
fooster/web/page.py
fooster/web/query.py
fooster/web/web.py
fooster_web-0.4.0rc1.dist-info/LICENSE
fooster_web-0.4.0rc1.dist-info/METADATA
fooster_web-0.4.0rc1.dist-info/WHEEL
fooster_web-0.4.0rc1.dist-info/namespace_packages.txt
fooster_web-0.4.0rc1.dist-info/top_level.txt
fooster_web-0.4.0rc1.dist-info/RECORD
